{
  "hash": "fed5cb0b",
  "configHash": "5f0c55f4",
  "lockfileHash": "e3b0c442",
  "browserHash": "7cdc7ea2",
  "optimized": {
    "prop-types": {
      "src": "../../node_modules/prop-types/index.js",
      "file": "prop-types.js",
      "fileHash": "ec1e9375",
      "needsInterop": true
    },
    "react": {
      "src": "../../node_modules/react/index.js",
      "file": "react.js",
      "fileHash": "750ea88d",
      "needsInterop": true
    },
    "react-dom/client": {
      "src": "../../node_modules/react-dom/client.js",
      "file": "react-dom_client.js",
      "fileHash": "848af1b9",
      "needsInterop": true
    },
    "react-router-dom": {
      "src": "../../node_modules/react-router-dom/dist/index.js",
      "file": "react-router-dom.js",
      "fileHash": "5599484e",
      "needsInterop": false
    }
  },
  "chunks": {
    "chunk-4ASWBRZ3": {
      "file": "chunk-4ASWBRZ3.js"
    },
    "chunk-O6O4HUXW": {
      "file": "chunk-O6O4HUXW.js"
    },
    "chunk-LQ2VYIYD": {
      "file": "chunk-LQ2VYIYD.js"
    }
  }
}